minimamba/__init__.py
minimamba/_version.py
minimamba/block.py
minimamba/config.py
minimamba/core.py
minimamba/model.py
minimamba/models.py
minimamba/norm.py
minimamba/s6.py
minimamba-1.0.3.dist-info/licenses/LICENSE
minimamba-1.0.3.dist-info/METADATA
minimamba-1.0.3.dist-info/WHEEL
minimamba-1.0.3.dist-info/top_level.txt
minimamba-1.0.3.dist-info/RECORD
