Metadata-Version: 2.4
Name: minimamba
Version: 1.0.3
Summary: Production-ready PyTorch implementation of Mamba (Selective State Space Model) with optimized parallel scan
Home-page: https://github.com/Xinguang/MiniMamba
Author: Xinguang
Author-email: Xinguang <minimanba.github@kansea.com>
License: MIT
Project-URL: Homepage, https://github.com/Xinguang/MiniMamba
Project-URL: Repository, https://github.com/Xinguang/MiniMamba
Project-URL: Documentation, https://github.com/Xinguang/MiniMamba/blob/main/README.md
Project-URL: Improvements, https://github.com/Xinguang/MiniMamba/blob/main/IMPROVEMENTS.md
Project-URL: Bug Reports, https://github.com/Xinguang/MiniMamba/issues
Keywords: mamba,state-space-model,transformer,attention,deep-learning,pytorch,nlp,time-series
Classifier: Development Status :: 5 - Production/Stable
Classifier: Intended Audience :: Developers
Classifier: Intended Audience :: Science/Research
Classifier: Operating System :: OS Independent
Classifier: Programming Language :: Python :: 3
Classifier: Programming Language :: Python :: 3.8
Classifier: Programming Language :: Python :: 3.9
Classifier: Programming Language :: Python :: 3.10
Classifier: Programming Language :: Python :: 3.11
Classifier: Programming Language :: Python :: 3.12
Classifier: Topic :: Scientific/Engineering :: Artificial Intelligence
Classifier: Topic :: Software Development :: Libraries :: Python Modules
Requires-Python: >=3.8
License-File: LICENSE
Requires-Dist: torch>=1.12.0
Requires-Dist: numpy>=1.20.0
Provides-Extra: dev
Requires-Dist: pytest>=6.0; extra == "dev"
Requires-Dist: pytest-cov>=2.10; extra == "dev"
Requires-Dist: black>=21.0; extra == "dev"
Requires-Dist: flake8>=3.8; extra == "dev"
Provides-Extra: examples
Requires-Dist: matplotlib>=3.0; extra == "examples"
Requires-Dist: pandas>=1.2.0; extra == "examples"
Requires-Dist: jupyter>=1.0; extra == "examples"
Dynamic: author
Dynamic: home-page
Dynamic: license-file
Dynamic: requires-python
